webracecondition/__init__.py
webracecondition/engine.py
webracecondition/frames.py
webracecondition/h2_connection.py
webracecondition/h2_tls_connection.py
webracecondition/roundtrip.py
webracecondition-0.0.14.dist-info/LICENSE
webracecondition-0.0.14.dist-info/METADATA
webracecondition-0.0.14.dist-info/WHEEL
webracecondition-0.0.14.dist-info/RECORD
