Metadata-Version: 2.1
Name: webracecondition
Version: 0.0.14
Summary: Tiny package to test webraceconditions
Home-page: https://github.com/hupe1980/webracecondition
License: MIT
Keywords: webracecondition,pentest,cybersecurity
Author: hupe1980
Requires-Python: >=3.11,<4.0
Classifier: License :: OSI Approved :: MIT License
Classifier: Programming Language :: Python
Classifier: Programming Language :: Python :: 3
Classifier: Programming Language :: Python :: 3.11
Classifier: Topic :: Security
Requires-Dist: scapy (>=2.5.0,<3.0.0)
Project-URL: Repository, https://github.com/hupe1980/webracecondition
